viihdecli/__init__.py
viihdecli/__main__.py
viihdecli/command_strings.py
viihdecli/duplicates.py
viihdecli/filter_recordings.py
viihdecli/naming_rules.py
viihdecli/print_recordings.py
viihdecli/version.py
viihdecli/viihde.py
viihdecli/viihdeapi.py
viihdecli/viihdedl.py
viihdecli/viihdehelp.py
viihdecli-0.22.1.dist-info/licenses/LICENSE
viihdecli-0.22.1.dist-info/METADATA
viihdecli-0.22.1.dist-info/WHEEL
viihdecli-0.22.1.dist-info/entry_points.txt
viihdecli-0.22.1.dist-info/top_level.txt
viihdecli-0.22.1.dist-info/RECORD
